oakemugym/__init__.py
oakemugym/oakemuenv.py
oakemugym/registration.py
oakemugym/ui/__init__.py
oakemugym/ui/ui.py
oakemugym-0.0.3.dist-info/LICENCE
oakemugym-0.0.3.dist-info/METADATA
oakemugym-0.0.3.dist-info/WHEEL
oakemugym-0.0.3.dist-info/RECORD
