Metadata-Version: 2.1
Name: oakemugym
Version: 0.0.3
Summary: Gymnasium environment for OakEmu.
Home-page: https://www.mrkwatkins.co.uk
License: MIT
Author: MrKWatkins
Author-email: mrkwatkins@gmail.com
Requires-Python: >=3.12,<3.13
Classifier: Development Status :: 3 - Alpha
Classifier: License :: OSI Approved :: MIT License
Classifier: Programming Language :: Python :: 3
Classifier: Programming Language :: Python :: 3.12
Requires-Dist: gymnasium[box2d] (>=0.29.1,<1.1.0)
Requires-Dist: oakemu (>=0.0.7,<0.0.8)
Project-URL: Repository, https://github.com/MrKWatkins/OakEmu-Gymnasium
